Workbook

Sheet October 26
B2: 2026 OCTOBER | F2: Настя | G2: Маша | H2: Сергій | I2: Аліна | J2: Олекса | K2: Андрій
A5: DX | B5: MGX | C5: SHIFTS | D5: HOURS | E5: D.LINE | F5: EMPL 1 | G5: EMPL 2 | H5: EMPL 3 | I5: EMPL 4 | J5: EMPL 5 | K5: EMPL 6 | L5: Total EMPL | M5: CLIENT IN
B6: DX-AIV-0197-005_SettAI_Halloween_Match2_DX-VEO-003-001_EN_60s | C6: 0.3 | D6: =C6*9 | F6: =D6*15 | L6: =SUM(F6:K6) | M6: =D6*35
B7: DX-AIV-0213-002_SettAI_SavePeonHalloween_DX-VEO-055-001_EN_30s | C7: 0.3 | D7: =C7*9 | L7: =SUM(F7:K7) | M7: =D7*35
B8: DX-AIV-0215-002_SettAI_HalloweenSkull_DX-VEO-055-001_EN_30s | C8: 0.3 | D8: =C8*9 | H8: =D8*15 | L8: =SUM(F8:K8) | M8: =D8*35
B9: DX-AIV-0218-002_SettAI_PuzzleHalloween_DX-VEO-055-001_EN_30s | C9: 0.3 | D9: =C9*9 | F9: =D9*15 | L9: =SUM(F9:K9) | M9: =D9*35
B10: DX-AIV-0222-003_SettAI_HalloweenRelax_DX-VEO-055-001_EN_30s | C10: 0.3 | D10: =C10*9 | L10: =SUM(F10:K10) | M10: =D10*35
B11: DX-AIV-0225-002_SettAI_HalloweenSave_DX-VEO-055-001_EN_60s | C11: 0.3 | D11: =C11*9 | F11: =D11*15 | L11: =SUM(F11:K11) | M11: =D11*35
B12: DX-AIV-0230-002_SettAI_HalloweenTower_ DX-VEO-055-001 _EN_60s | C12: 0.3 | D12: =C12*9 | G12: =D12*12 | L12: =SUM(F12:K12) | M12: =D12*35
B13: DX-AIV-0406-002_SettAI_InteractiveHalloween_DX-VEO-055-001_EN_60s | C13: 0.3 | D13: =C13*9 | G13: =D13*12 | L13: =SUM(F13:K13) | M13: =D13*35
B14: DX-AIV-0407-002_SettAI_GraveEscape_DX-VEO-055-001_EN_60s | C14: 0.3 | D14: =C14*9 | G14: =D14*12 | L14: =SUM(F14:K14) | M14: =D14*35
B15: DX-AIV-216-002_SettAI_HalloweenCircle_DX-VEO-055-001_EN_60s | C15: 0.3 | D15: =C15*9 | F15: =D15*15 | L15: =SUM(F15:K15) | M15: =D15*35
B16: DX-AIV-231-002_SettAI_Halloween_Spirals_DX-VEO-055-001_EN_60s | C16: 0.3 | D16: =C16*9 | L16: =SUM(F16:K16) | M16: =D16*35
A18: DD | B18: MGX | C18: SHIFTS | D18: HOURS | E18: D.LINE | F18: EMPL 1 | G18: EMPL 2 | H18: EMPL 3 | I18: EMPL 4 | J18: EMPL 5 | K18: EMPL 6 | L18: Total EMPL | M18: CLIENT IN
B19: DD-AIV-202-004_SettAI_HalloweenFireTrial_DD-VEO-059-001_EN_30s | C19: 0.3 | D19: =C19*9 | L19: =SUM(F19:K19) | M19: =D19*35
B20: DD-AIV-224-002_SettAI_HalloweenMario_DD-VEO-059-001_EN_30s | C20: 0.3 | D20: =C20*9 | G20: =D20*12 | L20: =SUM(F20:K20) | M20: =D20*35
B21: DD-AIV-225-002_SettAI_HalloweenTrap_DD-VEO-059-001_EN_30s | C21: 0.3 | D21: =C21*9 | G21: =D21*12 | L21: =SUM(F21:K21) | M21: =D21*35
B22: DD-AIV-227-002_SettAI_HalloweenBlastTreasure_DD-VEO-059-001_EN_24s | C22: 0.3 | D22: =C22*9 | L22: =SUM(F22:K22) | M22: =D22*35
B23: DD-AIV-228-002_SettAI_HalloweenBlastTreasure_DD-VEO-059-001_EN_30s | C23: 0.3 | D23: =C23*9 | L23: =SUM(F23:K23) | M23: =D23*35
B24: DD-AIV-229-002_SettAI_HalloweenMonopoly_DD-VEO-059-001_EN_30s | C24: 0.3 | D24: =C24*9 | L24: =SUM(F24:K24) | M24: =D24*35
B25: DD-AIV-231-002_SettAI_SpookyJackpot_DD-VEO-059-001_EN_30s | C25: 0.3 | D25: =C25*9 | H25: =D25*15 | L25: =SUM(F25:K25) | M25: =D25*35
B26: DD-AIV-233-002_SettAI_HalloweenKindomBuild_DD-VEO-059-001_EN_60s | C26: 0.3 | D26: =C26*9 | L26: =SUM(F26:K26) | M26: =D26*35
B27: DD-AIV-235-002_SettAI_WitchsPotion_DD-VEO-059-001_EN_30s | C27: 0.3 | D27: =C27*9 | L27: =SUM(F27:K27) | M27: =D27*35
B28: DD-AIV-239-002_SettAI_HalloweenDiamondBlast_DD-VEO-059-001_EN_30s | C28: 0.3 | D28: =C28*9 | L28: =SUM(F28:K28) | M28: =D28*35
A30: total | C30: =SUM(C6:C28) | D30: =SUM(D6:D28) | F30: =SUM(F6:F28) | G30: =SUM(G6:G28) | H30: =SUM(H6:H28) | I30: =SUM(I6:I28) | J30: =SUM(J6:J28) | K30: =SUM(K6:K28) | L30: =SUM(F30:K30) | M30: =SUM(M6:M28) | O30: UAH | P30: USD
F31: =F30*41.2 | G31: =G30*41.2 | H31: =H30*41.2 | I31: =I30*41.2 | J31: =J30*41.2 | K31: =K30*41.2 | L31: =L30*41.2 | M31: =M30*41.2 | N31: CLIENT IN | O31: =P31*41.2 | P31: =M30
N32: STUDIO (TAX) | O32: =P32*41.2 | P32: =P31-P31*0.05
N33: EMPL | O33: =P33*41.2 | P33: =L30
N34: STUDIO | O34: =P34*41.2 | P34: =P32-P33

Sheet February
B2: 2025 FEBRUARY | F2: Настя | G2: Маша | H2: Сергій | I2: Андрій
A5: DX | B5: MGX | C5: SHIFTS | D5: HOURS | E5: D.LINE | F5: EMPL 1 | G5: EMPL 2 | H5: EMPL 3 | I5: EMPL 4 | J5: Total EMPL | K5: STUDIO
B6: DX-B-011-010 | C6: 0.5 | D6: =C6*9 | F6: =D6*15 | K6: =D6*35
B7: DX-B-015-010 | C7: 0.5 | D7: =C7*9 | F7: =D7*15 | K7: =D7*35
B8: DX-B-020-002 | C8: 0.5 | D8: =C8*9 | F8: =D8*15 | K8: =D8*35
B9: DX-H-085-030_DE2024_Valentines+ DX-V-098-001_Hearts_DE_60s Length 30s | Hook Combo | C9: 0.3 | D9: =C9*9 | H9: =D9*15 | K9: =D9*35
B10: DX-V-002-001_Worlds_CupidBlow_DX-H-099-001_DE_30s | Hook Combo | C10: 0.3 | D10: =C10*9 | H10: =D10*15 | K10: =D10*35
B11: DX-V-098-001_Hearts_CupidBlow_DX-H-099-001_EN_60s | Hook Combo | C11: 0.3 | D11: =C11*9 | H11: =D11*15 | K11: =D11*35
B12: DX-V-098-001_Hearts_EN_60s Length ITR | Comp | C12: 0.3 | D12: =C12*9 | I12: =D12*12 | K12: =D12*35
B13: DX-V-098-001_Hearts_VdayRoses_DX-H-097-001_EN_30s | Hook Combo | C13: 0.3 | D13: =C13*9 | H13: =D13*15 | K13: =D13*35
B14: DX-V-098-001_Hearts_VDayRoses_DX-H-097-001_EN_60s | Hook Combo | C14: 0.3 | D14: =C14*9 | H14: =D14*15 | K14: =D14*35
B15: DX-V-098-002_Hearts_RT Length ITR | Comp | C15: 0.3 | D15: =C15*9 | I15: =D15*12 | K15: =D15*35
B16: DX-V-098-004_Hearts_DE2024_Valentines_DX-H-085-030_DE_60s | Hook Combo | C16: 0.3 | D16: =C16*9 | I16: =D16*12 | K16: =D16*35
B17: DX-V-106-003_BaseTrail_VDayRoses_DX-H-097-001_EN_30s | Hook Combo | C17: 0.3 | D17: =C17*9 | H17: =D17*15 | K17: =D17*35
B18: DX-V-107-002_RollBack_CupidBlow_DX-H-099-001_EN_60s | Hook Combo | C18: 0.3 | D18: =C18*9 | H18: =D18*15 | K18: =D18*35
B19: DX-B-020-002 dop resizes | C19: 0.3 | D19: =C19*9 | F19: =D19*15 | K19: =D19*35
B20: DX-V-084-005 | C20: 1 | D20: =C20*9 | K20: =D20*35
B21: DX-V-022-005 | C21: 0.5 | D21: =C21*9 | K21: =D21*35
B22: DX-V-022-005 | C22: 0.5 | D22: =C22*9 | K22: =D22*35
A27: DD | B27: MGX
B28: DD-V-250-031 | C28: 3 | D28: =C28*9 | H28: =D28*15 | K28: =D28*35
B29: DD-V-079-024 | C29: 1 | D29: =C29*9 | I29: =D29*12 | K29: =D29*35
B30: DD-V-079-025 | C30: 1 | D30: =C30*9 | I30: =D30*12 | K30: =D30*35
B31: DD-V-079-026 | C31: 1 | D31: =C31*9 | I31: =D31*12 | K31: =D31*35
B32: DD-V-079-027 | C32: 1 | D32: =C32*9 | I32: =D32*12 | K32: =D32*35
B33: DD-V-049-049 | C33: 0.3 | D33: =C33*9 | F33: =D33*15 | K33: =D33*35
B34: DD-V-229-008 | C34: 0.3 | D34: =C34*9 | F34: =D34*15 | K34: =D34*35
B35: DD-V-223-017 | C35: 0.3 | D35: =C35*9 | F35: =D35*15 | K35: =D35*35
B36: DD-V-223-018 | C36: 0.3 | D36: =C36*9 | F36: =D36*15 | K36: =D36*35
B37: DD-V-034-034 | C37: 0.3 | D37: =C37*9 | G37: =D37*12 | K37: =D37*35
B38: DD-V-034-035 | C38: 0.3 | D38: =C38*9 | G38: =D38*12 | K38: =D38*35
B39: DD-V-250-024 | C39: 0.5 | D39: =C39*9 | K39: =D39*35
B40: DD-V-143-003 | C40: 0.5 | D40: =C40*9 | K40: =D40*35
A44: total | C44: =SUM(C6:C43) | D44: =SUM(D6:D43) | F44: =SUM(F6:F33) | G44: =SUM(G6:G43) | H44: =SUM(H6:H33) | I44: =SUM(I6:I33) | J44: =SUM(F44:I44) | K44: =SUM(K6:K43) | M44: UAH | N44: USD
F45: =F44*40 | G45: =G44*40 | H45: =H44*40 | I45: =I44*40 | J45: =J44*40 | K45: =K44*40 | L45: CLIENT IN | M45: =N45*40 | N45: =K44
L46: STUDIO (TAX) | M46: =N46*40 | N46: =N45-N45*0.05
L47: EMPL | M47: =N47*40 | N47: =J44
L48: STUDIO | M48: =N48*40 | N48: =N46-N47

Sheet January
B2: 2025 JANUARY | F2: Настя | G2: Маша | H2: Сергій | I2: Андрій
A5: DX | B5: MGX | C5: SHIFTS | D5: HOURS | E5: D.LINE | F5: EMPL 1 | G5: EMPL 2 | H5: EMPL 3 | I5: EMPL 4 | J5: Total EMPL | K5: STUDIO
B6: DX-V-060-054 | C6: 0.3 | D6: =C6*9 | G6: =D6*12 | K6: =D6*35
B7: DX-V-060-055 | C7: 0.3 | D7: =C7*9 | G7: =D7*12 | K7: =D7*35
B8: DX-V-026-011 | C8: 0.3 | D8: =C8*9 | G8: =D8*12 | K8: =D8*35
B9: DX-V-015-027 | C9: 0.3 | D9: =C9*9 | G9: =D9*12 | K9: =D9*35
B10: DX-V-084-001 | C10: 0.3 | D10: =C10*9 | F10: =D10*15 | K10: =D10*35
B11: DX-V-088-004 | C11: 0.3 | D11: =C11*9 | F11: =D11*15 | K11: =D11*35
B12: DX-V-002-025 | C12: 0.3 | D12: =C12*9 | F12: =D12*15 | K12: =D12*35
B13: DX-V-032-020 | C13: 0.3 | D13: =C13*9 | F13: =D13*15 | K13: =D13*35
B14: DX-V-060-056 | C14: 0.3 | D14: =C14*9 | G14: =D14*12 | K14: =D14*35
B15: DX-V-033-019 | C15: 0.3 | D15: =C15*9 | F15: =D15*15 | K15: =D15*35
B16: DX-V-031-005 | C16: 0.3 | D16: =C16*9 | H16: =D16*15 | K16: =D16*35
B17: DX-V-033-020 | C17: 0.3 | D17: =C17*9 | G17: =D17*12 | K17: =D17*35
B18: DX-V-087-005 | C18: 0.3 | D18: =C18*9 | G18: =D18*12 | K18: =D18*35
B19: DX-V-060-060 | C19: 0.3 | D19: =C19*9 | F19: =D19*15 | K19: =D19*35
B20: DX-V-081-005 | C20: 0.3 | D20: =C20*9 | F20: =D20*15 | K20: =D20*35
B21: DX-V-017-016 | C21: 0.3 | D21: =C21*9 | F21: =D21*15 | K21: =D21*35
B22: DX-V-002-001 | C22: 0.5 | D22: =C22*9 | F22: =D22*15 | K22: =D22*35
B23: DX-V-007-002 | C23: 0.5 | D23: =C23*9 | H23: =D23*15 | K23: =D23*35
B24: DX-V-088-005 | C24: 0.3 | D24: =C24*9 | H24: =D24*15 | K24: =D24*35
B25: DX-V-088-006 | C25: 0.3 | D25: =C25*9 | G25: =D25*12 | K25: =D25*35
B26: DX-V-088-007 | C26: 0.3 | D26: =C26*9 | G26: =D26*12 | K26: =D26*35
B27: DX-V-084-002 | C27: 0.3 | D27: =C27*9 | G27: =D27*12 | K27: =D27*35
B28: DX-V-084-003 | C28: 0.3 | D28: =C28*9 | G28: =D28*12 | K28: =D28*35
B29: DX-V-084-004 | C29: 0.3 | D29: =C29*9 | G29: =D29*12 | K29: =D29*35
B30: DX-V-084-005 | C30: 0.3 | D30: =C30*9 | H30: =D30*15 | K30: =D30*35
B31: DX-V-073-003 | C31: 0.3 | D31: =C31*9 | H31: =D31*15 | K31: =D31*35
B32: DX-V-038-004 | C32: 0.5 | D32: =C32*9 | F32: =D32*15 | K32: =D32*35
B33: DX-V-087-002 | C33: 0.5 | D33: =C33*9 | F33: =D33*15 | K33: =D33*35
B34: DX-V-065-001 | C34: 0.5 | D34: =C34*9 | F34: =D34*15 | K34: =D34*35
B35: DX-V-051-008 | C35: 0.3 | D35: =C35*9 | G35: =D35*12 | K35: =D35*35
B36: DX-V-087-006 | C36: 0.3 | D36: =C36*9 | G36: =D36*12 | K36: =D36*35
B37: DX-V-074-001 | C37: 0.5 | D37: =C37*9 | F37: =D37*15 | K37: =D37*35
A41: DD | B41: MGX
B42: DD-V-045-009 | C42: 0.3 | D42: =C42*9 | G42: =D42*12 | K42: =D42*35
B43: DD-V-079-023 | C43: 0.3 | D43: =C43*9 | F43: =D43*15 | K43: =D43*35
B44: DD-V-126-033 | C44: 0.3 | D44: =C44*9 | G44: =D44*12 | K44: =D44*35
B45: DD-V-162-013 | C45: 0.3 | D45: =C45*9 | F45: =D45*15 | K45: =D45*35
B46: DD-V-162-014 | C46: 0.3 | D46: =C46*9 | F46: =D46*15 | K46: =D46*35
B47: DD-V-229-005 | C47: 0.3 | D47: =C47*9 | G47: =D47*12 | K47: =D47*35
B48: DD-V-229-006 | C48: 0.3 | D48: =C48*9 | G48: =D48*12 | K48: =D48*35
B49: DD-V-235-011 FR | C49: 0.3 | D49: =C49*9 | G49: =D49*12 | K49: =D49*35
B50: DD-V-235-011 DE | C50: 0.3 | D50: =C50*9 | G50: =D50*12 | K50: =D50*35
B51: DD-V-247-002 | C51: 0.3 | D51: =C51*9 | F51: =D51*15 | K51: =D51*35
B52: DD-V-255-002 | C52: 0.3 | D52: =C52*9 | F52: =D52*15 | K52: =D52*35
B53: DD-V-049-043 | C53: 0.3 | D53: =C53*9 | F53: =D53*15 | K53: =D53*35
B54: DD-V-144-034 | C54: 0.3 | D54: =C54*9 | F54: =D54*15 | K54: =D54*35
B55: DD-V-209-003 | C55: 0.3 | D55: =C55*9 | G55: =D55*12 | K55: =D55*35
B56: DD-V-049-044 | C56: 0.3 | D56: =C56*9 | F56: =D56*15 | K56: =D56*35
B57: DD-V-049-045 | C57: 0.3 | D57: =C57*9 | F57: =D57*15 | K57: =D57*35
B58: DD-V-056-009 | C58: 0.3 | D58: =C58*9 | G58: =D58*12 | K58: =D58*35
B59: DD-V-056-010 | C59: 0.3 | D59: =C59*9 | G59: =D59*12 | K59: =D59*35
B60: DD-V-126-034 | C60: 0.3 | D60: =C60*9 | G60: =D60*12 | K60: =D60*35
B61: DD-V-223-012 | C61: 0.3 | D61: =C61*9 | F61: =D61*15 | K61: =D61*35
B62: DD-V-223-013 | C62: 0.3 | D62: =C62*9 | F62: =D62*15 | K62: =D62*35
B63: DD-V-229-007 | C63: 0.3 | D63: =C63*9 | G63: =D63*12 | K63: =D63*35
B64: DD-V-126-035 | C64: 0.3 | D64: =C64*9 | G64: =D64*12 | K64: =D64*35
B65: DD-V-223-014 | C65: 0.5 | D65: =C65*9 | F65: =D65*15 | K65: =D65*35
B66: DD-V-223-015 | C66: 0.5 | D66: =C66*9 | F66: =D66*15 | K66: =D66*35
B67: DD-V-257-002 | C67: 4.5 | D67: =C67*9 | F67: =D67*15 | K67: =D67*35
B68: DD-V-049-050 | C68: 0.3 | D68: =C68*9 | G68: =D68*12 | K68: =D68*35
B69: DD-V-049-051 | C69: 0.3 | D69: =C69*9 | G69: =D69*12 | K69: =D69*35
B70: DD-V-049-053 | C70: 0.3 | D70: =C70*9 | G70: =D70*12 | K70: =D70*35
B71: DD-V-134-003 | C71: 0.3 | D71: =C71*9 | F71: =D71*15 | K71: =D71*35
B72: DD-V-188-002 | C72: 0.3 | D72: =C72*9 | F72: =D72*15 | K72: =D72*35
B73: DD-V-194-002 | C73: 0.3 | D73: =C73*9 | F73: =D73*15 | K73: =D73*35
A76: total | C76: =SUM(C6:C74) | D76: =SUM(D6:D74) | F76: =SUM(F6:F74) | G76: =SUM(G6:G75) | H76: =SUM(H6:H74) | I76: =SUM(I6:I74) | J76: =SUM(F76:I76) | K76: =SUM(K6:K75) | M76: UAH | N76: USD
F77: =F76*40 | G77: =G76*40 | H77: =H76*40 | I77: =I76*40 | J77: =J76*40 | K77: =K76*40 | L77: CLIENT IN | M77: =N77*40 | N77: =K76
L78: STUDIO (TAX) | M78: =N78*40 | N78: =N77-N77*0.05
L79: EMPL | M79: =N79*40 | N79: =J76
L80: STUDIO | M80: =N80*40 | N80: =N78-N79

Sheet December
B2: 2024 NOVEMBER | F2: Настя | G2: Маша | H2: Сергій | I2: Андрій
A5: DX | B5: MGX | C5: SHIFTS | D5: HOURS | E5: D.LINE | F5: EMPL 1 | G5: EMPL 2 | H5: EMPL 3 | I5: EMPL 4 | J5: Total EMPL | K5: STUDIO
B6: DX-V-060-014 | C6: 1 | D6: =C6*9 | F6: =D6*15 | K6: =D6*35
B7: DX-V-060-045 | C7: 0.6 | D7: =C7*9 | F7: =D7*15 | K7: =D7*35
B8: DX-V-060-046 | C8: 0.3 | D8: =C8*9 | G8: =D8*12 | K8: =D8*35
B9: DX-V-060-047 | C9: 0.3 | D9: =C9*9 | G9: =D9*12 | K9: =D9*35
B10: DX-V-060-048 | C10: 0.3 | D10: =C10*9 | G10: =D10*12 | K10: =D10*35
B11: DX-V-060-049 | C11: 0.3 | D11: =C11*9 | G11: =D11*12 | K11: =D11*35
B12: DX-V-060-023 | C12: 0.5 | D12: =C12*9 | F12: =D12*15 | K12: =D12*35
B13: DX-V-060-051 | C13: 0.3 | D13: =C13*9 | I13: =D13*12 | K13: =D13*35
B14: DX-V-073-002 | C14: 1 | D14: =C14*9 | I14: =D14*12 | K14: =D14*35
B15: DX-V-087-004 | C15: 0.5 | D15: =C15*9 | I15: =D15*12 | K15: =D15*35
B16: DX-V-060-014 | C16: 0.3 | D16: =C16*9 | F16: =D16*15 | K16: =D16*35
B17: DX-V-060-050 | C17: 0.3 | D17: =C17*9 | I17: =D17*12 | K17: =D17*35
B18: DX-V-032-011 | C18: 0.3 | D18: =C18*9 | G18: =D18*12 | K18: =D18*35
B19: DX-V-002-022 | C19: 0.3 | D19: =C19*9 | F19: =D19*15 | K19: =D19*35
B20: DX-V-015-025 | C20: 0.3 | D20: =C20*9 | G20: =D20*12 | K20: =D20*35
B21: DX-V-032-019 | C21: 0.3 | D21: =C21*9 | G21: =D21*12 | K21: =D21*35
B22: DX-V-033-016 | C22: 0.3 | D22: =C22*9 | G22: =D22*12 | K22: =D22*35
B23: DX-V-050-003 | C23: 0.3 | D23: =C23*9 | F23: =D23*15 | K23: =D23*35
B24: DX-V-033-017 | C24: 0.3 | D24: =C24*9 | G24: =D24*12 | K24: =D24*35
B25: DX-V-028-014 | C25: 0.3 | D25: =C25*9 | F25: =D25*15 | K25: =D25*35
B26: DX-V-060-052 | C26: 0.3 | D26: =C26*9 | F26: =D26*15 | K26: =D26*35
B27: DX-V-060-053 | C27: 0.5 | D27: =C27*9 | F27: =D27*15 | K27: =D27*35
B28: DX-V-017-010 | C28: 0.3 | D28: =C28*9 | G28: =D28*12 | K28: =D28*35
B29: DX-V-002-023 | C29: 0.3 | D29: =C29*9 | G29: =D29*12 | K29: =D29*35
B30: DX-V-017-011 | C30: 0.3 | D30: =C30*9 | G30: =D30*12 | K30: =D30*35
B31: DX-V-017-012 | C31: 0.3 | D31: =C31*9 | G31: =D31*12 | K31: =D31*35
B32: DX-V-017-013 | C32: 0.3 | D32: =C32*9 | G32: =D32*12 | K32: =D32*35
B33: DX-V-017-014 | C33: 0.3 | D33: =C33*9 | G33: =D33*12 | K33: =D33*35
B34: DX-V-017-015 | C34: 0.3 | D34: =C34*9 | G34: =D34*12 | K34: =D34*35
B35: DX-V-028-015 | C35: 0.3 | D35: =C35*9 | F35: $41 | K35: =D35*35
B36: DX-V-031-004 | C36: 0.3 | D36: =C36*9 | F36: $41 | K36: =D36*35
B37: DX-V-050-014 | C37: 0.3 | D37: =C37*9 | F37: $41 | K37: =D37*35
B38: DX-V-058-002 | C38: 0.3 | D38: =C38*9 | F38: $41 | K38: =D38*35
B39: DX-V-079-005 | C39: 0.3 | D39: =C39*9 | F39: $41 | K39: =D39*35
B40: DX-V-033-018 | C40: 0.3 | D40: =C40*9 | K40: =D40*35
A42: DD | B42: MGX
B43: DD-V-116-025 | C43: 0.3 | D43: =C43*9 | G43: =D44*12 | K43: =D43*35
B44: DD-V-186-003 | C44: 0.3 | D44: =C44*9 | G44: =D44*12 | K44: =D44*35
B45: DD-V-235-004 | C45: 0.3 | D45: =C45*9 | F45: =D45*15 | K45: =D45*35
B46: DD-V-235-005 | C46: 0.3 | D46: =C46*9 | F46: =D46*15 | K46: =D46*35
B47: DD-V-235-006 | C47: 0.3 | D47: =C47*9 | F47: =D47*15 | K47: =D47*35
B48: DD-V-034-030 | C48: 0.3 | D48: =C48*9 | F48: =D48*15 | K48: =D48*35
B49: DD-V-034-031 | C49: 0.3 | D49: =C49*9 | F49: =D49*15 | K49: =D49*35
B50: DD-V-034-032 | C50: 0.3 | D50: =C50*9 | F50: =D50*15 | K50: =D50*35
B51: DD-V-034-033 | C51: 0.3 | D51: =C51*9 | F51: =D51*15 | K51: =D51*35
B52: DD-V-049-039 | C52: 0.3 | D52: =C52*9 | G52: =D52*12 | K52: =D52*35
B53: DD-V-049-040 | C53: 0.3 | D53: =C53*9 | G53: =D53*12 | K53: =D53*35
B54: DD-V-049-041 | C54: 0.3 | D54: =C54*9 | G54: =D54*12 | K54: =D54*35
B55: DD-V-049-042 | C55: 0.3 | D55: =C55*9 | G55: =D55*12 | K55: =D55*35
A58: total | C58: =SUM(C6:C55) | D58: =SUM(D6:D55) | F58: =SUM(F6:F55) | G58: =SUM(G6:G57) | H58: =SUM(H6:H55) | I58: =SUM(I6:I55) | J58: =SUM(F58:I58) | K58: =SUM(K6:K57) | M58: UAH | N58: USD
F59: =F58*40 | G59: =G58*40 | H59: =H58*40 | I59: =I58*40 | J59: =J58*40 | K59: =K58*40 | L59: CLIENT IN | M59: =N59*40 | N59: =K58
L60: STUDIO (TAX) | M60: =N60*40 | N60: =N59-N59*0.05
L61: EMPL | M61: =N61*40 | N61: =J58
L62: STUDIO | M62: =N62*40 | N62: =N60-N61

Sheet November
B2: 2024 NOVEMBER | F2: Настя | G2: Маша | H2: Сергій | I2: Андрій
A5: DX | B5: MGX | C5: SHIFTS | D5: HOURS | E5: D.LINE | F5: EMPL 1 | G5: EMPL 2 | H5: EMPL 3 | I5: EMPL 4 | J5: Total EMPL | K5: STUDIO
B6: DX-V-060-023 | C6: 0.3 | D6: =C6*9 | F6: =D6*15 | K6: =D6*35
B7: DX-V-023-003 | C7: 1 | D7: =C7*9 | I7: =D7*12 | K7: =D7*35
B8: DX-V-002-001 | C8: 0.5 | D8: =C8*9 | I8: =D8*12 | K8: =D8*35
B9: DX-V-026-001 | C9: 0.5 | D9: =C9*9 | H9: =D9*15 | K9: =D9*35
B10: DX-V-015-015 | C10: 0.5 | D10: =C10*9 | F10: =D10*15 | K10: =D10*35
B11: DX-V-028-001 | C11: 0.5 | D11: =C11*9 | H11: =D11*15 | K11: =D11*35
B12: DX-V-026-009 | C12: 0.3 | D12: =C12*9 | H12: =D12*15 | K12: =D12*35
B13: DX-V-042-005 | C13: 0.3 | D13: =C13*9 | I13: =D13*12 | K13: =D13*35
B14: DX-V-065-002 | C14: 0.3 | D14: =C14*9 | F14: =D14*15 | K14: =D14*35
B15: DX-V-033-015 | C15: 0.3 | D15: =C15*9 | I15: =D15*12 | K15: =D15*35
B16: DX-V-026-010 | C16: 0.3 | D16: =C16*9 | F16: =D16*15 | K16: =D16*35
B17: DX-V-042-006 | C17: 0.3 | D17: =C17*9 | I17: =D17*12 | K17: =D17*35
B18: DX-V-051-001 | C18: 0.5 | D18: =C18*9 | H18: =D18*15 | K18: =D18*35
B19: DX-V-051-002 | C19: 0.5 | D19: =C19*9 | H19: =D19*15 | K19: =D19*35
B20: DX-V-088-003 | C20: 0.3 | D20: =C20*9 | F20: =D20*15 | K20: =D20*35
B21: DX-V-032-017 | C21: 0.5 | D21: =C21*9 | I21: =D21*12 | K21: =D21*35
B22: DX-V-079-003 | C22: 0.5 | D22: =C22*9 | H22: =D22*15 | K22: =D22*35
B23: DX-V-060-031 | C23: 0.3 | D23: =C23*9 | I23: =D23*12 | K23: =D23*35
B24: DX-V-060-030 | C24: 0.3 | D24: =C24*9 | F24: =D24*15 | K24: =D24*35
B25: DX-V-065-001 | C25: 0.5 | D25: =C25*9 | H25: =D25*15 | K25: =D25*35
B26: DX-V-033-014 | C26: 0.3 | D26: =C26*9 | H26: =D26*15 | K26: =D26*35
B27: DX-V-060-014 | C27: 0.5 | D27: =C27*9 | F27: =D27*15 | K27: =D27*35
B28: DX-V-032-002 | C28: 0.5 | D28: =C28*9 | F28: =D28*15 | K28: =D28*35
B29: DX-V-060-034 | C29: 0.3 | D29: =C29*9 | H29: =D29*15 | K29: =D29*35
B30: DX-V-083-002 | C30: 1 | D30: =C30*9 | H30: =D30*15 | K30: =D30*35
B31: DX-V-050-003 | C31: 0.5 | D31: =C31*9 | H31: =D31*15 | K31: =D31*35
B32: DX-V-060-035 | C32: 0.3 | D32: =C32*9 | H32: =D32*15 | K32: =D32*35
B33: DX-V-060-036 | C33: 0.3 | D33: =C33*9 | H33: =D33*15 | K33: =D33*35
B34: DX-V-060-037 | C34: 0.3 | D34: =C34*9 | H34: =D34*15 | K34: =D34*35
B35: DX-V-060-038 | C35: 0.3 | D35: =C35*9 | F35: =D35*15 | K35: =D35*35
B36: DX-V-060-039 | C36: 0.3 | D36: =C36*9 | F36: =D36*15 | K36: =D36*35
B37: DX-V-060-040 | C37: 0.3 | D37: =C37*9 | F37: =D37*15 | K37: =D37*35
B38: DX-V-060-041 | C38: 0.3 | D38: =C38*9 | I38: =D38*12 | K38: =D38*35
B39: DX-V-060-042 | C39: 0.3 | D39: =C39*9 | I39: =D39*12 | K39: =D39*35
B40: DX-V-060-043 | C40: 0.3 | D40: =C40*9 | I40: =D40*12 | K40: =D40*35
B41: DX-V-060-044 | C41: 0.3 | D41: =C41*9 | I41: =D41*12 | K41: =D41*35
B42: DX-V-083-004 | C42: 0.3 | D42: =C42*9 | H42: =D42*15 | K42: =D42*35
B44: 2D
C45: 0 | D45: =C45*9 | K45: =D45*35
A48: DD | B48: MGX
B49: DD-V-137-039 | C49: 0.5 | D49: =C49*9 | F49: =D49*15 | K49: =D49*35
B50: DD-V-202-001 | C50: 0.5 | D50: =C50*9 | F50: =D50*15 | K50: =D50*35
B51: DD-V-045-002 | C51: 0.5 | D51: =C51*9 | I51: =D51*12 | K51: =D51*35
B52: DD-V-078-001 | C52: 0.5 | D52: =C52*9 | H52: =D52*15 | K52: =D52*35
B55: 2D
C56: 0 | D56: =C56*9 | K56: =D56*35
A60: total | C60: =SUM(C6:C56) | D60: =SUM(D6:D57) | F60: =SUM(F6:F54) | G60: =SUM(G6:G59) | H60: =SUM(H6:H54) | I60: =SUM(I6:I54) | J60: =SUM(F60:I60) | K60: =SUM(K6:K59) | M60: UAH | N60: USD
F61: =F60*40 | G61: =G60*40 | H61: =H60*40 | I61: =I60*40 | J61: =J60*40 | K61: =K60*40 | L61: CLIENT IN | M61: =N61*40 | N61: =K60
L62: STUDIO (TAX) | M62: =N62*40 | N62: =N61-N61*0.05
L63: EMPL | M63: =N63*40 | N63: =J60
L64: STUDIO | M64: =N64*40 | N64: =N62-N63

Sheet October
B2: 2024 OCTOBER | F2: Настя | G2: Маша | H2: Сергій | I2: Андрій
A4: DX
A5: MGX | B5: October | C5: SHIFTS | D5: HOURS | E5: D.LINE | F5: EMPL 1 | G5: EMPL 2 | H5: EMPL 3 | I5: EMPL 4 | J5: Total EMPL | K5: STUDIO
B6: DX-V-041-005 | C6: 0.3 | D6: =C6*9 | I6: =D6*12 | K6: =D6*35
B7: DX-V-028-013 | C7: 0.3 | D7: =C7*9 | I7: =D7*12 | K7: =D7*35
B8: DX-V-032-001 | C8: 0.3 | D8: =C8*9 | H8: =D8*15 | K8: =D8*35
B9: DX-V-015-013 | C9: 0.3 | D9: =C9*9 | H9: =D9*15 | K9: =D9*35
B10: DX-V-026-008 | C10: 1 | D10: =C10*9 | I10: =D10*12 | K10: =D10*35
B11: DX-V-083-001 | C11: 0.5 | D11: =C11*9 | H11: =D11*15 | K11: =D11*35
B12: DX-V-060-012 | C12: 0.3 | D12: =C12*9 | I12: =D12*12 | K12: =D12*35
B13: DX-V-050-006 | C13: 0.3 | D13: =C13*9 | H13: =D13*15 | K13: =D13*35
B14: DX-V-050-009 | C14: 0.6 | D14: =C14*9 | F14: =D14*15 | K14: =D14*35
B15: DX-V-050-010 | C15: 0.3 | D15: =C15*9 | F15: =D15*15 | K15: =D15*35
B16: DX-V-050-011 | C16: 0.5 | D16: =C16*9 | H16: =D16*15 | K16: =D16*35
B17: DX-V-033-012 | C17: 0.3 | D17: =C17*9 | I17: =D17*12 | K17: =D17*35
B18: DX-V-033-013 | C18: 0.3 | D18: =C18*9 | I18: =D18*12 | K18: =D18*35
B19: DX-V-015-023 | C19: 0.3 | D19: =C19*9 | H19: =D19*15 | K19: =D19*35
B20: DX-V-015-024 | C20: 0.3 | D20: =C20*9 | H20: =D20*15 | K20: =D20*35
B21: DX-V-060-025 | C21: 0.5 | D21: =C21*9 | H21: =D21*15 | K21: =D21*35
B22: DX-V-032-009 | C22: 0.3 | D22: =C22*9 | I22: =D22*12 | K22: =D22*35
B23: DX-V-031-002 | C23: 0.3 | D23: =C23*9 | I23: =D23*12 | K23: =D23*35
B24: DX-V-050-007 | C24: 0.6 | D24: =C24*9 | I24: =D24*12 | K24: =D24*35
B25: DX-V-060-014 | C25: 0.5 | D25: =C25*9 | F25: =D25*15 | K25: =D25*35
B26: DX-V-060-020 | C26: 0.3 | D26: =C26*9 | H26: =D26*15 | K26: =D26*35
B27: DX-V-060-027 | C27: 0.3 | D27: =C27*9 | F27: =D27*15 | K27: =D27*35
A29: 2D
B30: DX-B-006-006 | C30: 0.3 | D30: =C30*9 | F30: =D30*15 | K30: =D30*35
B31: DX-B-057-001 | C31: 1 | D31: =C31*9 | F31: =D31*15 | K31: =D31*35
B32: DX-B-041-003 | C32: 0.5 | D32: =C32*9 | G32: =D32*10 | K32: =D32*35
B33: DX-B-041-004 | C33: 0.5 | D33: =C33*9 | G33: =D33*10 | K33: =D33*35
B34: =SUM(D6:D33)
A36: DD
A37: MGX
B38: DD-V-247-001 | C38: 1 | D38: =C38*9 | H38: =D38*15 | K38: =D38*35
B39: DD-V-235-001 | C39: 1 | D39: =C39*9 | I39: =D39*12 | K39: =D39*35
B40: DD-V-137-023 | C40: 0.5 | D40: =C40*9 | H40: =D40*15 | K40: =D40*35
B41: DD-V-045-002 | C41: 0.5 | D41: =C41*9 | H41: =D41*15 | K41: =D41*35
B42: DD-V-205-002 | C42: 0.3 | D42: =C42*9 | F42: =D42*15 | K42: =D42*35
B43: DD-V-219-002 | C43: 0.3 | D43: =C43*9 | F43: =D43*15 | K43: =D43*35
B44: DD-V-049-004 | C44: 2 | D44: =C44*9 | H44: =D44*15 | K44: =D44*35
B45: DD-V-116-003 | C45: 3.5 | D45: =C45*9 | I45: =D45*12 | K45: =D45*35
B46: DD-V-205-001 | C46: 0.5 | D46: =C46*9 | H46: =D46*15 | K46: =D46*35
A48: 2D
B49: DD-LO-038-001 | C49: 0.5 | D49: =C49*9 | F49: =D49*15 | K49: =D49*35
B50: =SUM(D38:D50)
A53: total | C53: =SUM(C6:C49) | D53: =SUM(D6:D50) | F53: =SUM(F6:F47) | G53: =SUM(G6:G52) | H53: =SUM(H6:H47) | I53: =SUM(I6:I47) | J53: =SUM(F53:I53) | K53: =SUM(K6:K52) | M53: UAH | N53: USD
F54: =F53*40 | G54: =G53*40 | H54: =H53*40 | I54: =I53*40 | J54: =J53*40 | K54: =K53*40 | L54: CLIENT IN | M54: =N54*40 | N54: =K53
H55: plus 68 | I55: plus 54 | L55: STUDIO (TAX) | M55: =N55*40 | N55: =N54-N54*0.05
L56: EMPL | M56: =N56*40 | N56: =J53
L57: STUDIO | M57: =N57*40 | N57: =N55-N56

Sheet September
B2: 2024 PROJECT NAME | F2: Настя | G2: Ріта | H2: Сергій | I2: Андрій
A5: MGX DX | B5: September | C5: SHIFTS | D5: HOURS | E5: D.LINE | F5: EMPL 1 | G5: EMPL 2 | H5: EMPL 3 | I5: EMPL 4 | J5: Total EMPL | K5: STUDIO | N5: UAH | O5: USD
B6: DX-V-026-001 | C6: 0.5 | D6: =C6*9 | H6: =D6*5 | I6: =D6*10 | K6: =D6*35 | M6: CLIENT IN | N6: =O6*40 | O6: =K98
B7: DX-V-026-007 | C7: 0.5 | D7: =C7*9 | H7: =D7*5 | I7: =D7*10 | K7: =D7*35 | M7: STUDIO (TAX) | N7: =O7*40 | O7: =O6-O6*0.05
B8: DX-V-050-004 | C8: 0.5 | D8: =C8*9 | H8: =D8*15 | K8: =D8*35 | M8: EMPL | N8: =O8*40 | O8: =J98
B9: DX-V-050-003 | C9: 0.5 | D9: =C9*9 | H9: =D9*15 | K9: =D9*35 | M9: STUDIO | N9: =O9*40 | O9: =O7-O8
B10: DX-V-042-002 | C10: 0.3 | D10: =C10*9 | H10: =D10*15 | K10: =D10*35
B11: DX-V-041-003 | C11: 0.3 | D11: =C11*9 | H11: =D11*15 | K11: =D11*35 | L11: EMPL | M11: COST | N11: 2PAY | O11: PAID
B12: DX-V-041-004 | C12: 0.3 | D12: =C12*9 | I12: =D12*10 | K12: =D12*35 | L12: EMPL 1 | M12: =F98 | N12: =M12-O12
B13: DX-V-060-011 | C13: 0.3 | D13: =C13*9 | H13: =D13*5 | I13: =D13*10 | K13: =D13*35 | L13: EMPL 2 | M13: =H98 | N13: =M13-O13
B14: DX-V-060-013 | C14: 0.3 | D14: =C14*9 | H14: =D14*5 | I14: =D14*10 | K14: =D14*35 | L14: EMPL 3 | M14: =G98 | N14: =M14-O14
B15: DX-V-060-005 | C15: 0.3 | D15: =C15*9 | H15: =D15*5 | I15: =D15*10 | K15: =D15*35 | L15: EMPL 4 | M15: =I98 | N15: =M15-O15
B16: DX-V-043-001 | C16: 0.5 | D16: =C16*9 | H16: =D16*15 | K16: =D16*35
B17: DX-V-028-009 | C17: 0.3 | D17: =C17*9 | I17: =D17*10 | K17: =D17*35
B18: DX-V-031-003 | C18: 0.3 | D18: =C18*9 | F18: =D18*15 | K18: =D18*35
B19: DX-V-033-009 | C19: 0.3 | D19: =C19*9 | F19: =D17*7 | I19: =D17*8 | K19: =D19*35
B20: DX-V-075-005 | C20: 0.3 | D20: =C20*9 | H20: =D20*15 | K20: =D20*35
B21: DX-V-075-007 | C21: 0.3 | D21: =C21*9 | I21: =D21*10 | K21: =D21*35
B22: DX-V-002-020 | C22: 0.3 | D22: =C22*9 | H22: =D22*15 | K22: =D22*35
B23: DX-V-028-010 | C23: 0.3 | D23: =C23*9 | H23: =D23*15 | K23: =D23*35
B24: DX-V-028-011 | C24: 0.3 | D24: =C24*9 | H24: =D24*15 | K24: =D24*35
B25: DX-V-028-012 | C25: 0.3 | D25: =C25*9 | H25: =D25*15 | K25: =D25*35
B26: DX-V-032-013 | C26: 0.3 | D26: =C26*9 | I26: =D26*10 | K26: =D26*35
B27: DX-V-032-014 | C27: 0.3 | D27: =C27*9 | I27: =D27*10 | K27: =D27*35
B28: DX-V-032-015 | C28: 0.3 | D28: =C28*9 | I28: =D28*10 | K28: =D28*35
B29: DX-V-033-010 | C29: 0.3 | D29: =C29*9 | I29: =D29*10 | K29: =D29*35
A30: Dop Fix Yaron | B30: DX-V-060-009 | C30: 0.5 | D30: =C30*9 | H30: =D30*15 | K30: =D30*35
A31: Dop Fix Yaron | B31: DX-V-060-010 | C31: 0.5 | D31: =C31*9 | H31: =D31*15 | K31: =D31*35
B32: DX-V-050-005 | C32: 0.3 | D32: =C32*9 | I32: =D32*12 | K32: =D32*35
B33: DX-V-015-018 | C33: 0.3 | D33: =C33*9 | I33: =D33*12 | K33: =D33*35
B34: DX-V-015-019 | C34: 0.3 | D34: =C34*9 | I34: =D34*12 | K34: =D34*35
B35: DX-V-015-020 | C35: 0.3 | D35: =C35*9 | I35: =D35*12 | K35: =D35*35
B36: DX-V-015-021 | C36: 0.3 | D36: =C36*9 | I36: =D36*12 | K36: =D36*35
B37: DX-V-051-004 | C37: 0.3 | D37: =C37*9 | H37: =D37*15 | K37: =D37*35
B38: DX-V-015-022 | C38: 0.3 | D38: =C38*9 | F38: =D38*15 | K38: =D38*35
B39: DX-V-051-005 | C39: 0.3 | D39: =C39*9 | H39: =D39*15 | K39: =D39*35
B40: DX-V-032-016 | C40: 0.3 | D40: =C40*9 | H40: =D40*15 | K40: =D40*35
B41: DX-V-079-003 | C41: 0.3 | D41: =C41*9 | I41: =D41*12 | K41: =D41*35
A44: MGX DD
B45: DD-V-049-032 | C45: 0.5 | D45: =C45*9 | H45: =D45*15 | K45: =D45*35
B46: DD-UGC-300-001 DD-V-162-011 | C46: 0.5 | D46: =C46*9 | H46: =D46*15 | K46: =D46*35
B47: DD-UGC-300-001 DD-V-162-012 | C47: 0.5 | D47: =C47*9 | H47: =D47*15 | K47: =D47*35
B48: DD-V-181-033 | C48: 0.05 | D48: =C48*9 | H48: =D48*15 | K48: =D48*35
B49: DD-V-181-034_US2023 | C49: 0.05 | D49: =C49*9 | H49: =D49*15 | K49: =D49*35
B50: DD-V-211-001 | C50: 0.05 | D50: =C50*9 | H50: =D50*15 | K50: =D50*35
B51: DD-V-221-001 | C51: 0.05 | D51: =C51*9 | I51: =D51*10 | K51: =D51*35
B52: DD-V-181-028 | C52: 0.05 | D52: =C52*9 | F52: =D52*15 | K52: =D52*35
B53: DD-V-181-035 | C53: 0.05 | D53: =C53*9 | F53: =D53*15 | K53: =D53*35
B54: DD-V-181-036 | C54: 0.05 | D54: =C54*9 | F54: =D54*15 | K54: =D54*35
B55: DD-V-181-029 | C55: 0.05 | D55: =C55*9 | F55: =D55*15 | K55: =D55*35
B56: DD-V-181-037 | C56: 0.05 | D56: =C56*9 | F56: =D56*15 | K56: =D56*35
B57: DD-V-181-038 | C57: 0.05 | D57: =C57*9 | F57: =D57*15 | K57: =D57*35
B58: DD-V-181-030 | C58: 0.05 | D58: =C58*9 | I58: =D58*10 | K58: =D58*35
B59: DD-V-181-039 | C59: 0.05 | D59: =C59*9 | I59: =D59*10 | K59: =D59*35
B60: DD-V-181-040 | C60: 0.05 | D60: =C60*9 | I60: =D60*10 | K60: =D60*35
B61: DD-V-181-031 | C61: 0.05 | D61: =C61*9 | I61: =D61*10 | K61: =D61*35
B62: DD-V-181-041 | C62: 0.05 | D62: =C62*9 | I62: =D62*10 | K62: =D62*35
B63: DD-V-181-042 | C63: 0.05 | D63: =C63*9 | I63: =D63*10 | K63: =D63*35
B64: DD-V-181-043 | C64: 0.05 | D64: =C64*9 | I64: =D64*10 | K64: =D64*35
B65: DD-V-181-044 | C65: 0.05 | D65: =C65*9 | I65: =D65*10 | K65: =D65*35
B66: DD-V-235-002 | C66: 1 | D66: =C66*9 | H66: =D66*15 | K66: =D66*35
B67: DD-V-078-055 | C67: 0.2 | D67: =C67*9 | H67: =D67*15 | K67: =D67*35
B68: DD-V-181-005 | C68: 0.1 | D68: =C68*9 | H68: =D68*15 | K68: =D68*35
B69: DD-V-126-032 | C69: 0.5 | D69: =C69*9 | I69: =D69*10 | K69: =D69*35
B70: DD-V-144-032 | C70: 0.5 | D70: =C70*9 | I70: =D70*10 | K70: =D70*35
B71: DD-V-049-031 | C71: 0.5 | D71: =C71*9 | H71: =D71*15 | K71: =D71*35
B72: DD-V-242-002 | C72: 0.5 | D72: =C72*9 | H72: =D72*15 | K72: =D72*35
B73: DD-V-078-056 | C73: 1 | D73: =C73*9 | I73: =D73*12 | K73: =D73*35
B74: DD-V-221-002 | C74: 0.5 | D74: =C74*9 | H74: =D74*15 | K74: =D74*35
B75: DD-V-233-002 | C75: 0.5 | D75: =C75*9 | H75: =D75*15 | K75: =D75*35
B76: DD-V-078-053 | C76: 0.5 | D76: =C76*9 | H76: =D76*15 | K76: =D76*35
B77: DD-V-078-054 | C77: 0.5 | D77: =C77*9 | I77: =D77*12 | K77: =D77*35
A80: 2D DX
B81: DX-FG-009-002 | C81: 0.5 | D81: =C81*9 | F81: =D81*15 | K81: =D81*35
B82: DX-SPS-004-006 | C82: 0.5 | D82: =C82*9 | F82: =D82*15 | K82: =D82*35
B83: DX-B-015-003 | C83: 0.5 | D83: =C83*9 | F83: =D83*5 | G83: =D83*10 | K83: =D83*35
B84: DX-B-011-008 | C84: 0.5 | D84: =C84*9 | F84: =D84*5 | G84: =D84*10 | K84: =D84*35
B85: DX-SS-011-001 | C85: 2 | D85: =C85*9 | F85: =D85*5 | G85: =D85*10 | K85: =D85*35
B86: DX-SS-011-002 | C86: 0.5 | D86: =C86*9 | F86: =D86*5 | G86: =D86*10 | K86: =D86*35
B87: DX-B-015-001 | C87: 0.5 | D87: =C87*9 | F87: =D87*15 | K87: =D87*35
B88: DX-B-034-001 | C88: 0.3 | D88: =C88*9 | F88: =D88*5 | G88: =D88*10 | K88: =D88*35
B89: DX-B-054-001 | C89: 0.5 | D89: =C89*9 | F89: =D89*5 | G89: =D89*10 | K89: =D89*35
B90: DX-LO-014-002 | C90: 0.5 | D90: =C90*9 | F90: =D90*15 | K90: =D90*35
B91: DX-LO-014-003 | C91: 0.5 | D91: =C91*9 | F91: =D91*15 | K91: =D91*35
A93: 2D DD
B94: DD-B-092-002 | C94: 0.2 | D94: =C94*9 | F94: =D94*5 | G94: =D94*10 | K94: =D94*35
B95: DD-LO-021-002 | C95: 0.5 | D95: =C95*9 | F95: =D95*15 | K95: =D95*35
C98: =SUM(C6:C95) | D98: =SUM(D6:D95) | F98: =SUM(F6:F92) | G98: =SUM(G6:G92) | H98: =SUM(H6:H92) | I98: =SUM(I6:I92) | J98: =SUM(F98:I98) | K98: =SUM(K6:K97)
F99: =F98*40 | G99: =G98*40 | H99: =H98*40 | I99: =I98*40 | J99: =J98*40 | K99: =K98*40

Sheet August
B2: 2024 PROJECT NAME | F2: Настя | G2: Сергій
B5: August | C5: SHIFTS | D5: HOURS | E5: D.LINE | F5: EMPL 1 | G5: EMPL 2 | H5: Total EMPL | I5: STUDIO | L5: UAH | M5: USD
A6: 1 | B6: DX-V-032-004_TinderSwipe_DX-V-026-001_EN_59s | C6: 0.7 | D6: =C6*9 | F6: =D6*15 | I6: =D6*35 | K6: CLIENT IN | L6: =M6*40 | M6: =I45
A7: 2 | B7: DX-V-032-005_TinderSwipe_NoCursor | C7: 0.5 | D7: =C7*9 | G7: =D7*15 | I7: =D7*35 | K7: STUDIO (TAX) | L7: =M7*40 | M7: =M6-M6*0.05
A8: 3 | B8: DX-V-032-008_TinderSwipe_DX-H-048-001 | C8: 0.3 | D8: =C8*9 | G8: =D8*15 | I8: =D8*35 | K8: EMPL | L8: =M8*40 | M8: =H45
A9: 4 | B9: DX-V-002-016_Worlds_NLVillage_NL_30s LOC to EN | C9: 0.5 | D9: =C9*9 | G9: =D9*15 | I9: =D9*35 | K9: STUDIO | L9: =M9*40 | M9: =M7-M8
A10: 5 | B10: DX-V-060-001_MKTrail_Netherlands | LOC*1: NL | C10: 0.5 | D10: =C10*9 | F10: =D10*15 | I10: =D10*35
A11: 6 | B11: DX-V-060-002_MKTrail_Netherlands_DX-H-067-001 (NLClogs) | C11: 0.5 | D11: =C11*9 | F11: =D11*15 | I11: =D11*35 | J11: EMPL | K11: COST | L11: 2PAY | M11: PAID
A12: 7 | B12: DX-V-060-003_MKTrail_Netherlands_DX-H-066-001 (NLFlowerBlow) | C12: 0.5 | D12: =C12*9 | F12: =D12*15 | I12: =D12*35 | J12: EMPL 1 | K12: =F45 | L12: =K12-M12
A13: 8 | B13: DX-V-060-005_MKTrail_HLWN_DD-H-170-001(FrankensteinTickle) | C13: 0.5 | D13: =C13*9 | I13: =D13*35 | J13: EMPL 2 | K13: =G45 | L13: =K13-M13
A14: 9 | B14: DX-V-060-006_MKTrail_Netherlands_DX-H-045-003 (LeaningOnCloud_WIN-SFX) | C14: 0.5 | D14: =C14*9 | F14: =D14*15 | I14: =D14*35
A15: 10 | B15: DX-V-060-007_MKTrail_Netherlands_DX-H-045-004 (LeaningOnCloud_FAIL-SFX) | C15: 0.5 | D15: =C15*9 | F15: =D15*15 | I15: =D15*35
A16: 11 | B16: DX-V-033-008_BuildInPuzzle_DX-V-017-003 (WorldsIntro)_PTE | C16: 1.5 | D16: =C16*9 | I16: =D16*35
A17: 12 | B17: DD-V-079-001_GameplayPeoject_Blue_DE_30s | C17: 0.5 | D17: =C17*9 | F17: =D17*15 | I17: =D17*35
A18: 13 | B18: DD-V-079-020_GameplayProject_Blue_DD-H-073-001(HookXmas2021_Snowball)_DE_00s | C18: 0.3 | D18: =C18*9 | F18: =D18*15 | I18: =D18*35
A19: 14 | B19: DD-V-079-019_GameplayProject_Blue_DD-H-177-001(HookBeerFest)_DE_00s | C19: 0.3 | D19: =C19*9 | F19: =D19*15 | I19: =D19*35
A20: 15 | B20: DD-V-126-030_PullThePin_DD-H-177-001(HookBeerFest)_DE_00s | C20: 0.3 | D20: =C20*9 | G20: =D20*15 | I20: =D20*35
A21: 16 | B21: DD-V-123-002_BeerPong_DD-H-177-001(HookBeerFest)_DE_00s | C21: 0.3 | D21: =C21*9 | G21: =D21*15 | I21: =D21*35
A22: 17 | B22: DD-V-116-023_Trail_Xmas_DE_DD-H-073-001(HookXmas2021_Snowball)_DE_00s | C22: 0.3 | D22: =C22*9 | G22: =D22*15 | I22: =D22*35
A23: 18 | B23: DD-V-078-051_RoyalMatch_NoDiceTryYourself_DD-H-073-001(HookXmas2021_Snowball)_DE_00s | C23: 0.3 | D23: =C23*9 | G23: =D23*15 | I23: =D23*35
A24: 19 | B24: DD-V-078-050_RoyalMatch_NoDiceTryYourself_DD-H-177-001(HookBeerFest)_DE_00s | C24: 0.3 | D24: =C24*9 | G24: =D24*15 | I24: =D24*35
A25: 20 | B25: DD-V-122-002_LocalizedIntro_DD-H-177-001_DE-ASO | C25: 1 | D25: =C25*9 | G25: =D25*15 | I25: =D25*35
A26: 21 | B26: DD-V-126-031_PullThePin_DD-H-073-001(HookXmas2021_Snowball)_DE_00 | C26: 0.3 | D26: =C26*9 | G26: =D26*15 | I26: =D26*35
A27: 22 | B27: DD-V-224-002_TeamChat_ShortVer_15s | comp | C27: 1 | D27: =C27*9 | G27: =D27*15 | I27: =D27*35
A28: 23 | B28: DD-V-224-003_TeamChat_DD-H-175-001(80sIntro)_EN_45s | comp | C28: 0.5 | D28: =C28*9 | G28: =D28*15 | I28: =D28*35
A29: 24 | B29: DD-V-224-004_TeamChat_DD-V-144-001(SimpleStealBlast)_EN_60s | comp | C29: 0.5 | D29: =C29*9 | G29: =D29*15 | I29: =D29*35
A30: 25 | B30: DD-V-223-002_FirstPlace_CTA_15s | comp | C30: 0.5 | D30: =C30*9 | G30: =D30*15 | I30: =D30*35
A31: 26 | B31: DD-V-223-003_FirstPlace_DD-H-175-001_EN_45s | comp | C31: 0.5 | D31: =C31*9 | G31: =D31*15 | I31: =D31*35
A32: 27 | B32: DD-V-223_004_FirstPlace_DD-V-049-001(Trail_Knight)_EN_60s | comp | C32: 0.5 | D32: =C32*9 | G32: =D32*15 | I32: =D32*35
A33: 28 | B33: DD-V-049-025_Trail_KnightCoins_EN LOC to IT | C33: 0.5 | D33: =C33*9 | I33: =D33*35
A34: 29 | B34: DD-V-229-001_Coins&Coins_EN LOC to IT- 0.5 shift | C34: 0.5 | D34: =C34*9 | G34: =D34*15 | I34: =D34*35
A35: 30 | B35: DD-V-212-001_FairytaleAttack_EN 30 LOC to IT- 0.5 shift | C35: 0.5 | D35: =C35*9 | F35: =D35*15 | I35: =D35*35
A36: 31 | B36: DD-V-221-001 LuckySpins [By RHQ] LOC to IT- 0.5 shift | C36: 0.5 | D36: =C36*9 | I36: =D36*35
A37: 32 | B37: DD-V-195-001_Stickers_LastSticker-Retro-1Left_RT_EN LOC to IT- 0.5 shift | C37: 0.5 | D37: =C37*9 | F37: =D37*15 | I37: =D37*35
A38: 33 | B38: DD-V-226-001_StickerGameplay [by RHQ] LOC to IT- 0.5 shift | C38: 0.5 | D38: =C38*9 | I38: =D38*35
A39: 34 | B39: DD-V-078-011_RoyalMatch_NoDiceDoBetter LOC to IT- 0.5 shift | C39: 0.5 | D39: =C39*9 | F39: =D39*15 | I39: =D39*35
A40: 35 | B40: DD-V-144-001_SimpleStealBlast_Pirate LOC to IT- 0.5 shift | C40: 0.5 | D40: =C40*9 | F40: =D40*15 | I40: =D40*35
A41: 36 | B41: DD-B-083-001_FreeFallSkyDive LOC to IT- 0.3 shift | C41: 0.3 | D41: =C41*9 | I41: =D41*35
A42: 37 | B42: DD-B-077-002_StPatrickSlide_PeonWaterSlide_RT | Design | C42: 0.5 | D42: =C42*9 | F42: =D42*15 | I42: =D42*35
A43: 38 | B43: DX-V-032-008_TinderSwipe_DX-H-048-001_StackExplosion | Comp & Resizes | C43: 0.3 | D43: =C43*9 | G43: =D43*15 | I43: =D43*35
C45: =SUM(C6:C44) | D45: =SUM(D6:D44) | F45: =SUM(F6:F44) | G45: =SUM(G6:G44) | H45: =F45+G45 | I45: =SUM(I6:I44)
F46: =F45*40 | G46: =G45*40 | H46: =H45*40 | I46: =I45*40

Sheet July
B2: 2024 PROJECT NAME | F2: Настя | G2: Сергій
F3: 2Dpaint | G3: 2Dvideo
B4: JULY | C4: SHIFTS | D4: HOURS | E4: D.LINE | F4: EMPL 2 | G4: EMPL 3 | H4: Total EMPL | I4: STUDIO | N4: Rates/h
L5: USD | M5: UAH | N5: 50
A6: 1 | B6: DD-SS-001-002_PurpleRibbonOriginals_OneWord_LOC_DE+ES-SP, ES-LA+FR | design | C6: 1 | D6: =C6*9 | F6: =D6*N17 | I6: =D6*35 | K6: CLIENT IN | L6: =I18 | M6: =L6*36.95 | N6: 45
A7: 2 | B7: DX-B-011-006_TreasureTrail_Netherlands_PTE | Resizes: | C7: 0.5 | D7: =C7*9 | F7: =D7*N17 | I7: =D7*35 | K7: STUDIO (TAX) | L7: =L6-L6*0.05 | M7: =L7*36.95 | N7: 40
A8: 3 | B8: DX-V-031-001_PeonChest_EN 30s | LOC*1: NL | Comp & Resizes | C8: 0.6 | D8: =C8*9 | G8: =D8*N13 | I8: =D8*35 | K8: EMPL | L8: =H18 | M8: =L8*36.95 | N8: 35
A9: 4 | B9: DX-V-028-001_ImpossibleLevel | LOC*2: NL+ES-LA | Comp | C9: 0.6 | D9: =C9*9 | G9: =D9*N13 | I9: =D9*35 | K9: STUDIO | L9: =L7-L8 | M9: =L9*36.95 | N9: 32
A10: 5 | B10: DX-V-022-001_BuildSequence_ASO | LOC*1: NL | Comp | C10: 0.5 | D10: =C10*9 | G10: =D10*N13 | I10: =D10*35 | N10: 30
A11: 6 | B11: DX-V-032-002_TinderSwipe_RenaissanceFair_20s | C11: 0.5 | D11: =C11*9 | G11: =D11*N13 | I11: =D11*35 | J11: EMPL | K11: COST | L11: PAID | M11: 2PAY | N11: 25
A12: 7 | B12: DX-B-015-003_LeaningDominoDreams_PlayNow | C12: 0.25 | D12: =C12*9 | G12: =D12*N13 | I12: =D12*35 | J12: EMPL 1 | K12: =F18 | M12: =K12-L12 | N12: 20
A13: 8 | B13: DX-B-026-002_BeachLife_RT | LOC*1 - NL | Design | C13: 0.25 | D13: =C13*9 | F13: =D13*N17 | I13: =D13*35 | J13: EMPL 2 | K13: =G18 | M13: =K13-L13 | N13: 15
A14: 9 | B14: DX-B-012-001_BeachCastle | LOC*3: ES-LA+DE+NL | Design | C14: 0.3 | D14: =C14*9 | F14: =D14*N17 | I14: =D14*35 | N14: 13
A15: 10 | B15: DX-B-019-001_PileofDominos LOC*1: ES-LA + DE | Design | C15: 0.3 | D15: =C15*9 | F15: =D15*N17 | I15: =D15*35 | N15: 12
A16: 11 | B16: DD-V-229-Coins&Coins_EN - 15,30,45 & 60s | C16: 1.2 | D16: =C16*9 | G16: =D16*N13 | I16: =D16*35 | N16: 11
N17: 10
C18: =SUM(C5:C17) | D18: =SUM(D6:D17) | F18: =SUM(F6:F16) | G18: =SUM(G5:G16) | H18: =SUM(F18:G18) | I18: =SUM(I6:I16)

Sheet June
B2: 2024 PROJECT NAME | F2: Mary | G2: Настя | H2: Сергій | I2: Настя
F3: 2Dpaint | G3: 2Dpaint | H3: 2Dvideo | I3: 2Dbanner
B4: JUNE | C4: SHIFTS | D4: HOURS | E4: D.LINE | F4: EMPL 1 | G4: EMPL 2 | H4: EMPL 3 | I4: EMPL 4 | J4: Total EMPL | K4: STUDIO | P4: Rates/h
N5: USD | O5: UAH | P5: 50
A6: 1 | B6: DD-B-087-001_AllOfThisKingdom | C6: 1.1 | D6: =C6*9 | F6: =D6*P12 | K6: =D6*P7 | M6: CLIENT IN | N6: =K12 | O6: =N6*36.95 | P6: 45
A7: 2 | B7: DD-SPS-002-007_DiceThrowPeons_PurpleBanner | C7: 1.5 | D7: =C7*9 | G7: =D7*E17 | K7: =D7*P11 | M7: STUDIO (TAX) | N7: =N6-N6*0.05 | O7: =N7*36.95 | P7: 40
A8: 3 | B8: DX-B-032-001_Skateboard + DX-B-032-002_Skateboard_RT | C8: 1.5 | D8: =C8*9 | F8: =D8*P12 | K8: =D8*P7 | M8: EMPL | N8: =J12 | O8: =N8*36.95 | P8: 35
A9: 4 | B9: DX-V-015-016_SimpleIntro_DX-H-009-002(PeonDominoThrow_WildDom)_EN_26s | C9: 0.25 | D9: =C9*9 | H9: =D9*P13 | K9: =D9*P9 | M9: STUDIO | N9: =N7-N8 | O9: =N9*36.95 | P9: 32
A10: 5 | B10: DX-V-028-005_ImpossibleLevel_DX-H-054-001(Pinata)_EN_24s | C10: 0.25 | D10: =C10*9 | H10: =D10*P13 | K10: =D10*P9 | P10: 30
L11: EMPL | M11: COST | N11: PAID | O11: 2PAY | P11: 25
C12: =SUM(C6:C11) | D12: =SUM(D6:D11) | F12: =SUM(F5:F11) | G12: =SUM(G5:G11) | H12: =SUM(H5:H11) | J12: =SUM(F12:H12) | K12: =SUM(K6:K11) | L12: EMPL 1 | M12: =F12 | O12: =M12-N12 | P12: 20
L13: EMPL 2 | M13: =G12 | O13: =M13-N13 | P13: 15
L14: EMPL 3 | M14: =H12 | O14: =M14-N14 | P14: 13
A48: 16
A49: 17
C61: =SUM(C48:C49) | D61: =SUM(D48:D49) | G61: =SUM(G48:G49) | H61: =SUM(H48:H49) | J61: =SUM(G61:H61) | K61: =SUM(K48:K49)

Sheet Employeers
E4: LISENBART FILM CREW
B6: name | C6: phone | E6: email | F6: name of bank | G6: bank card | H6: IBAN | I6: ІПН
A7: 1 | B7: Лащенко Сергій Олексійович | C7: +380 93 763 1347 | E7: lashenko285@gmail.com | F7: Monobank | G7: 4441111039612886 | H7: UA433220010000026202353175173 | I7: 3276811970
A8: 2 | B8: Анастасія Сиченко | C8: +380 99 550 5455 | E8: cat44cat22@gmail.com | F8: Monobank | G8: 4441114424460887 | H8: UA173220010000026202314266322
A9: 3 | B9: Андрій Миглін | C9: +380 99 608 9025 | E9: andrii.myhlin@gmail.com | F9: Monobank | G9: 5168752085544776 | H9: UA643052990000026201875784751 | I9: 3734505291
A10: 4 | B10: Терлецька Марія Максимівна | F10: Monobank | H10: UA683220010000026202353816766 | I10: 3781707605
A11: 5 | B11: Лавренишин Анатлоій | F11: Приват | H11: UA433052990000026207663260641
B12: Маргарита Бездітко | C12: +380 73 123 0042 | E12: rita.bezditko@gmail.com | F12: Monobank | G12: 4441114427187438

Sheet Invoices
C3: Every 20th day of Month
B4: INVOICES
B6: Month | C6: Description | D6: Quantity | E6: Price, USD | F6: Total
A7: 1 | B7: June | C7: DD/DX | D7: 41.4 | E7: 1488 | F7: =SUM(E7:E29)
A8: 2 | B8: July | C8: DD/DX | D8: =July!D18 | E8: =July!L6
A9: 3 | B9: August | C9: DD/DX | D9: =August!D45 | E9: =August!I45
A10: 4 | B10: September | C10: DD/DX | D10: =September!D98 | E10: =September!K98
A11: 5 | B11: October | C11: DD/DX | D11: =October!D53 | E11: =October!N54
A12: 6 | B12: November | C12: DD/DX | D12: =November!D60 | E12: =November!N61
A13: 7 | B13: December | C13: DD/DX | D13: =December!D58 | E13: =December!N59
A14: 8 | B14: Jabuary | C14: DD/DX | D14: =January!D76 | E14: =January!N77
A15: 9 | B15: Febraury | C15: DD/DX | D15: =February!D44 | E15: =February!N45
